README
setup.py
datapkggui/__init__.py
datapkggui/lib.py
datapkggui/main.py
datapkggui/operations.py
datapkggui.egg-info/PKG-INFO
datapkggui.egg-info/SOURCES.txt
datapkggui.egg-info/dependency_links.txt
datapkggui.egg-info/entry_points.txt
datapkggui.egg-info/not-zip-safe
datapkggui.egg-info/requires.txt
datapkggui.egg-info/top_level.txt
datapkggui/gui/__init__.py
datapkggui/gui/base.py
datapkggui/gui/maingui.py
datapkggui/gui/packagegui.py
datapkggui/res/__init__.py
tests/__init__.py
tests/test_lib.py