Metadata-Version: 1.0
Name: datapkggui
Version: 0.2.2
Summary: datapkggui (data package GUI): wxPython GUI for datapkg: data packaging system and utilities
Home-page: http://task3.cc/projects/datapkggui
Author: Daniel Graziotin
Author-email: d@danielgraziotin.it
License: BSD 2-Clause
Keywords: data,packaging,component,tool,GUI
Platform: UNKNOWN
